pwrdrvr/microapps/nextjsdemoappcdk/__init__.py
pwrdrvr/microapps/nextjsdemoappcdk/py.typed
pwrdrvr/microapps/nextjsdemoappcdk/_jsii/__init__.py
pwrdrvr/microapps/nextjsdemoappcdk/_jsii/microapps-app-nextjs-demo-cdk@0.7.0.jsii.tgz
pwrdrvr.microapps.nextjsdemoappcdk-0.7.0.dist-info/LICENSE
pwrdrvr.microapps.nextjsdemoappcdk-0.7.0.dist-info/METADATA
pwrdrvr.microapps.nextjsdemoappcdk-0.7.0.dist-info/WHEEL
pwrdrvr.microapps.nextjsdemoappcdk-0.7.0.dist-info/top_level.txt
pwrdrvr.microapps.nextjsdemoappcdk-0.7.0.dist-info/RECORD
